<?xml version="1.0" encoding="utf-8"?>
<rule>
	<name>Active Setup autostart registry entry was modified [A0100]</name>
	<severity>Information</severity>
	<Operations>
		<Operation type="RegSetValue">
			<operator type="AND">
				<Condition component="RegistryItem" property="Key" condition="ends" value="StubPath" />
				<operator type="OR">
					<Condition component="RegistryItem" property="Key" condition="contains" value="SOFTWARE\Microsoft\Active Setup\Installed Components" />
					<Condition component="RegistryItem" property="Key" condition="contains" value="SOFTWARE\Wow6432Node\Microsoft\Active Setup\Installed Components" />
				</operator>
			</operator>
		</Operation>
	</Operations>
</rule>