<?xml version="1.0" encoding="utf-8"?>
<rule>
  <ParentProcess>
    <operator type="AND">
      <Condition component="LiveGrid" property="Popularity" condition="greater" value="10000" />
          <operator type="OR">
              <Condition component="FileItem" property="Name" condition="is" value="AcroRd32" />
              <Condition component="FileItem" property="Name" condition="is" value="AcroRd64" />
          </operator>
    </operator>
  </ParentProcess>
  <Process>
    <operator type="AND">
      <Condition component="LiveGrid" property="Popularity" condition="greater" value="10000" />
      <Condition component="FileItem" property="Path" condition="starts" value="%WINDIR%" />
          <operator type="OR">
                <Condition component="FileItem" property="Name" condition="is" value="powershell" />
                <Condition component="FileItem" property="Name" condition="is" value="cscript" />
                <Condition component="FileItem" property="Name" condition="is" value="wscript" />
                <Condition component="FileItem" property="Name" condition="is" value="cmd" />
          </operator>
    </operator>
  </Process>
<name>Acrobat Reader has invoked script interpreter [D405]</name>
</rule>